sphinx_qsp
