Metadata-Version: 1.1
Name: sphinx-quickstart-plus
Version: 0.3.5
Summary: Python documentation generator
Home-page: https://github.com/pashango2/sphinx-qsp
Author: Toshiyuki Ishii
Author-email: pashango2@gmail.com
License: Free
Platform: any
Classifier: Development Status :: 2 - Pre-Alpha
Classifier: Environment :: Console
Classifier: Environment :: Web Environment
Classifier: Intended Audience :: Developers
Classifier: Intended Audience :: Education
Classifier: License :: Freeware
Classifier: Operating System :: OS Independent
Classifier: Programming Language :: Python
Classifier: Programming Language :: Python :: 2
Classifier: Programming Language :: Python :: 3
Classifier: Framework :: Sphinx
Classifier: Framework :: Sphinx :: Extension
Classifier: Framework :: Sphinx :: Theme
Classifier: Topic :: Documentation
Classifier: Topic :: Documentation :: Sphinx
Classifier: Topic :: Text Processing
Classifier: Topic :: Utilities
